{
    "abd1b5f7-e19e-482d-bc61-4abd70cdff2f": {
        "file": "th03_07.txt",
        "type": "work",
        "title": "Maniacal Princess",
        "usertag": [
            "th03"
        ],
        "tagroute": [
            "东方/东方原曲/ZUN/东方旧作原曲/东方整数作原曲/th03"
        ],
        "tag": [
            "th03",
            "东方梦时空",
            "东方",
            "touhou",
            "东方原曲",
            "ZUN",
            "东方旧作原曲",
            "东方整数作原曲"
        ],
        "alias": [
            "Maniacal Princess"
        ],
        "copyright": [
            "Blargzargo"
        ]
    }
}