{
    "ea059928-2377-34f2-bc4b-6c155e909762": {
        "file": "th03_02.txt",
        "type": "work",
        "title": "Selection",
        "usertag": [
            "th03"
        ],
        "tagroute": [
            "东方/东方原曲/ZUN/东方旧作原曲/东方整数作原曲/th03"
        ],
        "tag": [
            "th03",
            "东方梦时空",
            "东方",
            "touhou",
            "东方原曲",
            "ZUN",
            "东方旧作原曲",
            "东方整数作原曲"
        ],
        "alias": [
            "Selection"
        ],
        "copyright": [
            "Blargzargo",
            "Wobuffet3"
        ]
    }
}