{
    "a1b79cf4-3f54-343d-b76a-a45cc6574e40": {
        "file": "th06_16.txt",
        "type": "work",
        "title": "紅より儚い永遠",
        "usertag": [
            "th06"
        ],
        "tagroute": [
            "东方/东方原曲/ZUN/东方新作原曲/东方整数作原曲/th06"
        ],
        "tag": [
            "th06",
            "东方红魔乡",
            "东方",
            "touhou",
            "东方原曲",
            "ZUN",
            "东方新作原曲",
            "东方整数作原曲"
        ],
        "alias": [
            "比红色更虚无的永远"
        ],
        "copyright": [
            "ZUN"
        ]
    }
}